{"minVersion": "0.4", "class": "DepictionTabView", "tabs": [{"class": "DepictionStackView", "tabname": "Details", "views": [{"class": "DepictionSubheaderView", "useMargins": true, "title": "Compatible with iOS 14.0 +"}, {"class": "DepictionMarkdownView", "markdown": " <p>Enable App Library on iPad.</p> <p>Known issue: App Library in Landscape orientation is not maximized.</p>", "useSpacing": true, "useRawFormat": true}], "xPadding": 10}, {"class": "DepictionStackView", "tabname": "Latest Changes", "views": [{"class": "DepictionSubheaderView", "title": "Version 1.0.1"}, {"class": "DepictionMarkdownView", "markdown": "- Fixed homescreen widgets in sidebar not appearing right after respring"}, {"class": "DepictionSeparatorView"}, {"class": "DepictionSubheaderView", "title": "Version 1.0.0"}, {"class": "DepictionMarkdownView", "markdown": "- Initial release"}]}], "headerImage": "https://poomsmart.github.io/repo/features/applibraryforipad.png"}