{"minVersion": "0.4", "class": "DepictionTabView", "tabs": [{"class": "DepictionStackView", "tabname": "Details", "views": [{"class": "DepictionSubheaderView", "useMargins": true, "title": "Compatible with iOS 12.0 to 14.4.2"}, {"class": "DepictionMarkdownView", "markdown": "<p>Latest emojis for iOS 12.0 - 14.4</p> <p><a href=\"https://poomsmart.github.io/repo/emoji10.html\">** Follow instructions on installing emoji font here, otherwise emojis will render incorrectly**</a></p>", "useSpacing": true, "useRawFormat": true}, {"class": "DepictionSeparatorView"}, {"class": "DepictionTableTextView", "title": "Developer", "text": "PoomSmart"}], "xPadding": 10}, {"class": "DepictionStackView", "tabname": "Latest Changes", "views": [{"class": "DepictionSubheaderView", "title": "Version 1.1.1"}, {"class": "DepictionMarkdownView", "markdown": "- Release version"}]}]}